itime/__init__.py
py_itime-0.0.4.dist-info/LICENSE
py_itime-0.0.4.dist-info/METADATA
py_itime-0.0.4.dist-info/WHEEL
py_itime-0.0.4.dist-info/top_level.txt
py_itime-0.0.4.dist-info/RECORD
