Metadata-Version: 2.1
Name: py-itime
Version: 0.0.4
Summary: Time package supporting chain call
Home-page: https://github.com/AvinsWang/py-itime
Author: Avins Wang
Author-email: avinswang@gmail.com
License: LGPL-3.0
Download-URL: http://pypi.python.org/pypi/py-itime/
Keywords: py-itime,python time
Platform: UNKNOWN
Classifier: Topic :: Utilities
Classifier: Natural Language :: English
Classifier: Operating System :: OS Independent
Classifier: Intended Audience :: Developers
Classifier: License :: OSI Approved :: GNU Lesser General Public License v3 (LGPLv3)
Classifier: Programming Language :: Python :: 3.6
License-File: LICENSE
